autocalc/__init__.py
autocalc/_version.py
autocalc/autocalc.py
autocalc/tools.py
autocalc-0.2.1.dist-info/LICENSE
autocalc-0.2.1.dist-info/METADATA
autocalc-0.2.1.dist-info/WHEEL
autocalc-0.2.1.dist-info/top_level.txt
autocalc-0.2.1.dist-info/RECORD
